{
  "date" : "Mon, 03 Jul, 2023 17:56:37 +0000",
  "doco" : "For each file: start is seconds after start activity occurred. Length = milliseconds activity took",
  "files" : [
    {
      "name" : "/fsh-generated/resources/ImplementationGuide-ans.fhir.fr.cds.json",
      "size" : 7252,
      "processes" : [
        {
          "activity" : "load",
          "start" : 27,
          "length" : 56
        },
        {
          "activity" : "checkR4R4B",
          "start" : 30,
          "length" : 4
        },
        {
          "activity" : "generateNarratives",
          "start" : 30,
          "length" : 58
        },
        {
          "activity" : "validate",
          "start" : 41,
          "length" : 613
        },
        {
          "activity" : "scanForUsageStats",
          "start" : 42,
          "length" : 1
        },
        {
          "activity" : "validate",
          "start" : 42,
          "length" : 1
        },
        {
          "activity" : "generate1",
          "start" : 42,
          "length" : 121
        },
        {
          "activity" : "generate2",
          "start" : 49,
          "length" : 86
        },
        {
          "activity" : "generateValidationPack",
          "start" : 76,
          "length" : 2
        },
        {
          "activity" : "scanExamplesForR5",
          "start" : 96,
          "length" : 1
        }
      ]
    },
    {
      "name" : "fsh-generated/resources/StructureDefinition-cds-bundle-transaction-creation.json",
      "size" : 11188,
      "processes" : [
        {
          "activity" : "loadResources",
          "start" : 26,
          "length" : 38
        },
        {
          "activity" : "load-configure",
          "start" : 26,
          "length" : 3
        },
        {
          "activity" : "load",
          "start" : 26,
          "length" : 74
        },
        {
          "activity" : "generateSnapshots",
          "start" : 27,
          "length" : 1204
        },
        {
          "activity" : "generateNarratives",
          "start" : 30,
          "length" : 664
        },
        {
          "activity" : "validate",
          "start" : 32,
          "length" : 5072
        },
        {
          "activity" : "checkConformanceResources",
          "start" : 42,
          "length" : 2
        },
        {
          "activity" : "scanForUsageStats",
          "start" : 42,
          "length" : 6
        },
        {
          "activity" : "generate1",
          "start" : 42,
          "length" : 1360
        },
        {
          "activity" : "generate2",
          "start" : 49,
          "length" : 6115
        },
        {
          "activity" : "generateValidationPack",
          "start" : 76,
          "length" : 35
        },
        {
          "activity" : "scanProfilesForR5",
          "start" : 96,
          "length" : 1
        },
        {
          "activity" : "scanExamplesForR5",
          "start" : 96,
          "length" : 4
        }
      ]
    },
    {
      "name" : "fsh-generated/resources/SearchParameter-cds-careteam-participant-end.json",
      "size" : 595,
      "processes" : [
        {
          "activity" : "loadResources",
          "start" : 26,
          "length" : 10
        },
        {
          "activity" : "load",
          "start" : 26,
          "length" : 20
        },
        {
          "activity" : "load",
          "start" : 27,
          "length" : 11
        },
        {
          "activity" : "load",
          "start" : 27,
          "length" : 1
        },
        {
          "activity" : "generateNarratives",
          "start" : 31,
          "length" : 22
        },
        {
          "activity" : "validate",
          "start" : 41,
          "length" : 13
        },
        {
          "activity" : "generate1",
          "start" : 43,
          "length" : 6
        },
        {
          "activity" : "generate2",
          "start" : 55,
          "length" : 17
        }
      ]
    },
    {
      "name" : "fsh-generated/resources/StructureDefinition-cds-fr-related-person.json",
      "size" : 2023,
      "processes" : [
        {
          "activity" : "loadResources",
          "start" : 26,
          "length" : 14
        },
        {
          "activity" : "load",
          "start" : 26,
          "length" : 19
        },
        {
          "activity" : "generateSnapshots",
          "start" : 28,
          "length" : 158
        },
        {
          "activity" : "generateNarratives",
          "start" : 31,
          "length" : 136
        },
        {
          "activity" : "validate",
          "start" : 37,
          "length" : 435
        },
        {
          "activity" : "scanForUsageStats",
          "start" : 42,
          "length" : 1
        },
        {
          "activity" : "generate1",
          "start" : 43,
          "length" : 279
        },
        {
          "activity" : "generate2",
          "start" : 55,
          "length" : 1197
        },
        {
          "activity" : "generateValidationPack",
          "start" : 76,
          "length" : 8
        }
      ]
    },
    {
      "name" : "fsh-generated/resources/SearchParameter-cds-practitionerrole-nameex.json",
      "size" : 659,
      "processes" : [
        {
          "activity" : "loadResources",
          "start" : 26,
          "length" : 9
        },
        {
          "activity" : "load",
          "start" : 26,
          "length" : 13
        },
        {
          "activity" : "load",
          "start" : 27,
          "length" : 10
        },
        {
          "activity" : "generateNarratives",
          "start" : 31,
          "length" : 4
        },
        {
          "activity" : "validate",
          "start" : 41,
          "length" : 2
        },
        {
          "activity" : "generate1",
          "start" : 43,
          "length" : 5
        },
        {
          "activity" : "generate2",
          "start" : 56,
          "length" : 12
        },
        {
          "activity" : "generateValidationPack",
          "start" : 76,
          "length" : 1
        }
      ]
    },
    {
      "name" : "fsh-generated/resources/StructureDefinition-cds-ihe-careteam.json",
      "size" : 5098,
      "processes" : [
        {
          "activity" : "loadResources",
          "start" : 26,
          "length" : 18
        },
        {
          "activity" : "load",
          "start" : 26,
          "length" : 21
        },
        {
          "activity" : "generateSnapshots",
          "start" : 28,
          "length" : 152
        },
        {
          "activity" : "checkR4R4B",
          "start" : 30,
          "length" : 1
        },
        {
          "activity" : "generateNarratives",
          "start" : 31,
          "length" : 112
        },
        {
          "activity" : "validate",
          "start" : 38,
          "length" : 249
        },
        {
          "activity" : "generate1",
          "start" : 43,
          "length" : 251
        },
        {
          "activity" : "generate2",
          "start" : 56,
          "length" : 1002
        },
        {
          "activity" : "generateValidationPack",
          "start" : 76,
          "length" : 6
        },
        {
          "activity" : "scanExamplesForR5",
          "start" : 96,
          "length" : 1
        }
      ]
    },
    {
      "name" : "fsh-generated/resources/CapabilityStatement-CDSCreateurRestful.json",
      "size" : 3382,
      "processes" : [
        {
          "activity" : "loadResources",
          "start" : 26,
          "length" : 13
        },
        {
          "activity" : "load-configure",
          "start" : 26,
          "length" : 1
        },
        {
          "activity" : "load",
          "start" : 26,
          "length" : 20
        },
        {
          "activity" : "generateNarratives",
          "start" : 31,
          "length" : 9
        },
        {
          "activity" : "validate",
          "start" : 41,
          "length" : 104
        },
        {
          "activity" : "generate1",
          "start" : 44,
          "length" : 28
        },
        {
          "activity" : "generate2",
          "start" : 57,
          "length" : 32
        },
        {
          "activity" : "generateValidationPack",
          "start" : 76,
          "length" : 1
        }
      ]
    },
    {
      "name" : "fsh-generated/resources/SearchParameter-cds-careteam-start.json",
      "size" : 535,
      "processes" : [
        {
          "activity" : "loadResources",
          "start" : 26,
          "length" : 9
        },
        {
          "activity" : "load",
          "start" : 26,
          "length" : 16
        },
        {
          "activity" : "load",
          "start" : 27,
          "length" : 9
        },
        {
          "activity" : "generateNarratives",
          "start" : 31,
          "length" : 4
        },
        {
          "activity" : "validate",
          "start" : 41,
          "length" : 1
        },
        {
          "activity" : "generate1",
          "start" : 44,
          "length" : 5
        },
        {
          "activity" : "generate2",
          "start" : 57,
          "length" : 12
        },
        {
          "activity" : "generateValidationPack",
          "start" : 76,
          "length" : 1
        }
      ]
    },
    {
      "name" : "fsh-generated/resources/SearchParameter-cds-patient-birthplace.json",
      "size" : 502,
      "processes" : [
        {
          "activity" : "loadResources",
          "start" : 26,
          "length" : 9
        },
        {
          "activity" : "load",
          "start" : 26,
          "length" : 16
        },
        {
          "activity" : "load",
          "start" : 27,
          "length" : 11
        },
        {
          "activity" : "generateNarratives",
          "start" : 31,
          "length" : 3
        },
        {
          "activity" : "validate",
          "start" : 41,
          "length" : 1
        },
        {
          "activity" : "validate",
          "start" : 42,
          "length" : 1
        },
        {
          "activity" : "generate1",
          "start" : 44,
          "length" : 6
        },
        {
          "activity" : "generate2",
          "start" : 57,
          "length" : 7
        },
        {
          "activity" : "generateExampleZip",
          "start" : 76,
          "length" : 1
        }
      ]
    },
    {
      "name" : "fsh-generated/resources/StructureDefinition-cds-organization-orga-int.json",
      "size" : 2478,
      "processes" : [
        {
          "activity" : "loadResources",
          "start" : 26,
          "length" : 14
        },
        {
          "activity" : "scan",
          "start" : 26,
          "length" : 1
        },
        {
          "activity" : "load",
          "start" : 26,
          "length" : 16
        },
        {
          "activity" : "generateSnapshots",
          "start" : 28,
          "length" : 83
        },
        {
          "activity" : "generateNarratives",
          "start" : 31,
          "length" : 74
        },
        {
          "activity" : "validate",
          "start" : 38,
          "length" : 154
        },
        {
          "activity" : "scanForUsageStats",
          "start" : 42,
          "length" : 1
        },
        {
          "activity" : "generate1",
          "start" : 44,
          "length" : 162
        },
        {
          "activity" : "generate2",
          "start" : 57,
          "length" : 561
        },
        {
          "activity" : "generateValidationPack",
          "start" : 76,
          "length" : 4
        }
      ]
    },
    {
      "name" : "fsh-generated/resources/SearchParameter-cds-careteam-end.json",
      "size" : 519,
      "processes" : [
        {
          "activity" : "loadResources",
          "start" : 26,
          "length" : 9
        },
        {
          "activity" : "scan",
          "start" : 26,
          "length" : 1
        },
        {
          "activity" : "load",
          "start" : 26,
          "length" : 10
        },
        {
          "activity" : "load",
          "start" : 27,
          "length" : 10
        },
        {
          "activity" : "generateNarratives",
          "start" : 31,
          "length" : 4
        },
        {
          "activity" : "validate",
          "start" : 41,
          "length" : 2
        },
        {
          "activity" : "generate1",
          "start" : 44,
          "length" : 5
        },
        {
          "activity" : "generate2",
          "start" : 58,
          "length" : 8
        }
      ]
    },
    {
      "name" : "fsh-generated/resources/StructureDefinition-cds-bundle-transaction-maj.json",
      "size" : 11143,
      "processes" : [
        {
          "activity" : "loadResources",
          "start" : 26,
          "length" : 34
        },
        {
          "activity" : "load",
          "start" : 26,
          "length" : 50
        },
        {
          "activity" : "generateSnapshots",
          "start" : 28,
          "length" : 848
        },
        {
          "activity" : "generateNarratives",
          "start" : 31,
          "length" : 647
        },
        {
          "activity" : "validate",
          "start" : 38,
          "length" : 1393
        },
        {
          "activity" : "checkConformanceResources",
          "start" : 42,
          "length" : 1
        },
        {
          "activity" : "scanForUsageStats",
          "start" : 42,
          "length" : 3
        },
        {
          "activity" : "generate1",
          "start" : 44,
          "length" : 1280
        },
        {
          "activity" : "generate2",
          "start" : 58,
          "length" : 3533
        },
        {
          "activity" : "generateValidationPack",
          "start" : 76,
          "length" : 34
        },
        {
          "activity" : "scanExamplesForR5",
          "start" : 96,
          "length" : 3
        }
      ]
    },
    {
      "name" : "fsh-generated/resources/SearchParameter-cds-careteam-participant-start.json",
      "size" : 607,
      "processes" : [
        {
          "activity" : "loadResources",
          "start" : 26,
          "length" : 9
        },
        {
          "activity" : "load",
          "start" : 26,
          "length" : 11
        },
        {
          "activity" : "load",
          "start" : 27,
          "length" : 9
        },
        {
          "activity" : "generateNarratives",
          "start" : 32,
          "length" : 5
        },
        {
          "activity" : "validate",
          "start" : 41,
          "length" : 2
        },
        {
          "activity" : "generate1",
          "start" : 45,
          "length" : 6
        },
        {
          "activity" : "generate2",
          "start" : 62,
          "length" : 9
        }
      ]
    },
    {
      "name" : "fsh-generated/resources/CapabilityStatement-CDSConsommateur.json",
      "size" : 12327,
      "processes" : [
        {
          "activity" : "loadResources",
          "start" : 26,
          "length" : 22
        },
        {
          "activity" : "load",
          "start" : 27,
          "length" : 28
        },
        {
          "activity" : "checkR4R4B",
          "start" : 30,
          "length" : 1
        },
        {
          "activity" : "generateNarratives",
          "start" : 32,
          "length" : 15
        },
        {
          "activity" : "validate",
          "start" : 41,
          "length" : 55
        },
        {
          "activity" : "generate1",
          "start" : 45,
          "length" : 28
        },
        {
          "activity" : "generate2",
          "start" : 62,
          "length" : 10
        },
        {
          "activity" : "makeDependencies",
          "start" : 68,
          "length" : 1
        },
        {
          "activity" : "generateValidationPack",
          "start" : 76,
          "length" : 2
        }
      ]
    },
    {
      "name" : "fsh-generated/resources/StructureDefinition-cds-bundle-response-recherche.json",
      "size" : 9104,
      "processes" : [
        {
          "activity" : "loadResources",
          "start" : 26,
          "length" : 40
        },
        {
          "activity" : "load-configure",
          "start" : 26,
          "length" : 1
        },
        {
          "activity" : "load",
          "start" : 26,
          "length" : 46
        },
        {
          "activity" : "generateSnapshots",
          "start" : 29,
          "length" : 772
        },
        {
          "activity" : "generateNarratives",
          "start" : 32,
          "length" : 581
        },
        {
          "activity" : "validate",
          "start" : 40,
          "length" : 1084
        },
        {
          "activity" : "checkConformanceResources",
          "start" : 42,
          "length" : 1
        },
        {
          "activity" : "scanForUsageStats",
          "start" : 42,
          "length" : 3
        },
        {
          "activity" : "generate1",
          "start" : 45,
          "length" : 1382
        },
        {
          "activity" : "generate2",
          "start" : 62,
          "length" : 2548
        },
        {
          "activity" : "generateValidationPack",
          "start" : 76,
          "length" : 33
        },
        {
          "activity" : "scanExamplesForR5",
          "start" : 96,
          "length" : 2
        }
      ]
    },
    {
      "name" : "fsh-generated/resources/CapabilityStatement-CDSCreateurTransaction.json",
      "size" : 1554,
      "processes" : [
        {
          "activity" : "loadResources",
          "start" : 26,
          "length" : 11
        },
        {
          "activity" : "load",
          "start" : 27,
          "length" : 17
        },
        {
          "activity" : "generateNarratives",
          "start" : 32,
          "length" : 6
        },
        {
          "activity" : "validate",
          "start" : 41,
          "length" : 3
        },
        {
          "activity" : "generate1",
          "start" : 47,
          "length" : 8
        },
        {
          "activity" : "generate2",
          "start" : 64,
          "length" : 5
        },
        {
          "activity" : "generateValidationPack",
          "start" : 76,
          "length" : 1
        }
      ]
    },
    {
      "name" : "fsh-generated/resources/CapabilityStatement-CDSGestionnaire.json",
      "size" : 13728,
      "processes" : [
        {
          "activity" : "loadResources",
          "start" : 26,
          "length" : 25
        },
        {
          "activity" : "load",
          "start" : 27,
          "length" : 59
        },
        {
          "activity" : "checkR4R4B",
          "start" : 30,
          "length" : 1
        },
        {
          "activity" : "generateNarratives",
          "start" : 32,
          "length" : 17
        },
        {
          "activity" : "validate",
          "start" : 41,
          "length" : 27
        },
        {
          "activity" : "generate1",
          "start" : 47,
          "length" : 35
        },
        {
          "activity" : "generate2",
          "start" : 64,
          "length" : 18
        },
        {
          "activity" : "generateValidationPack",
          "start" : 76,
          "length" : 1
        }
      ]
    }
  ]
}
